mport/__init__.py
mport/mio.py
mport/examples/__init__.py
mport/examples/rgb_led.py
mport/examples/rgb_led_drive.py
mport-0.1.1.dist-info/LICENSE
mport-0.1.1.dist-info/METADATA
mport-0.1.1.dist-info/WHEEL
mport-0.1.1.dist-info/top_level.txt
mport-0.1.1.dist-info/RECORD
